genescraper/__init__.py
genescraper/__main__.py
genescraper/static/assets/icons8-info-16.png
genescraper/static/css/styles.css
genescraper/static/js/scripts.js
genescraper/templates/index.html
genescraper-0.1.2.dist-info/LICENSE
genescraper-0.1.2.dist-info/METADATA
genescraper-0.1.2.dist-info/WHEEL
genescraper-0.1.2.dist-info/entry_points.txt
genescraper-0.1.2.dist-info/top_level.txt
genescraper-0.1.2.dist-info/RECORD
