Metadata-Version: 2.1
Name: genescraper
Version: 0.1.2
Summary: A Flask web application that lets you scroll through GeneCard's gene summaries, granted you provide a list of genes.
Author: Branco Heuts
Author-email: brancoheuts@gmail.com
License: The MIT License (MIT)
Project-URL: Homepage, https://github.com/branco-heuts/genescraper
Keywords: GeneCard,Webscraping,Gene Summary
Classifier: License :: OSI Approved :: MIT License
Classifier: Programming Language :: Python :: 3
Classifier: Operating System :: OS Independent
Classifier: Intended Audience :: Science/Research
Requires-Python: >=3.10
License-File: LICENSE
Requires-Dist: beautifulsoup4 (>=4.11.1)
Requires-Dist: Flask (>=2.2.2)
Requires-Dist: pandas (>=1.4.4)
Requires-Dist: tqdm (>=4.64.0)
